gui_args_framework/__init__.py
gui_args_framework/args_window.py
gui_args_framework/fields.py
gui_args_framework/main_thread.py
gui_args_framework/rpc_call.py
gui_args_framework-1.3.0.dist-info/METADATA
gui_args_framework-1.3.0.dist-info/WHEEL
gui_args_framework-1.3.0.dist-info/top_level.txt
gui_args_framework-1.3.0.dist-info/RECORD
