Metadata-Version: 2.4
Name: gui-args-framework
Version: 1.3.0
Summary: A framework to create a GUI for a Python console application.
Home-page: https://github.com/fomalhaut88/gui-args-framework
Author: Alexander Fomalhaut
License: MIT
Project-URL: Homepage, https://pypi.org/project/gui-args-framework/
Project-URL: Documentation, https://fomalhaut88.github.io/gui-args-framework/
Project-URL: Source, https://github.com/fomalhaut88/gui-args-framework
Project-URL: Issues, https://github.com/fomalhaut88/gui-args-framework/issues
Keywords: gui qt
Classifier: Intended Audience :: Developers
Classifier: Topic :: Software Development :: Libraries
Classifier: License :: OSI Approved :: MIT License
Classifier: Programming Language :: Python :: 3
Classifier: Programming Language :: Python :: 3.12
Requires-Python: >=3.12
Requires-Dist: PyQt5>=5.15
Dynamic: author
Dynamic: classifier
Dynamic: description
Dynamic: description-content-type
Dynamic: home-page
Dynamic: keywords
Dynamic: license
Dynamic: project-url
Dynamic: requires-dist
Dynamic: requires-python
Dynamic: summary
